gryszka_config_package/__init__.py
gryszka_config_package/config.yml
gryszka_config_package/main.py
gryszka_config_package-0.1.2.dist-info/LICENSE
gryszka_config_package-0.1.2.dist-info/METADATA
gryszka_config_package-0.1.2.dist-info/WHEEL
gryszka_config_package-0.1.2.dist-info/top_level.txt
gryszka_config_package-0.1.2.dist-info/RECORD
