Metadata-Version: 2.1
Name: gryszka_config_package
Version: 0.1.2
Summary: A package to read configuration from a YAML file
Author-email: Gryszka <romanowicz.g@gmail.com>
License-File: LICENSE
Requires-Dist: pyyaml
